codex32/__init__.py
codex32/bech32.py
codex32/bip93.py
codex32/checksums.py
codex32/errors.py
codex32/py.typed
codex32/segwit_addr.py
codex32-0.6.1.dist-info/licenses/LICENSE
codex32-0.6.1.dist-info/METADATA
codex32-0.6.1.dist-info/WHEEL
codex32-0.6.1.dist-info/top_level.txt
codex32-0.6.1.dist-info/RECORD
