Metadata-Version: 2.4
Name: codex32
Version: 0.6.1
Summary: Python reference implementation for codex32 (BIP93) and codex32-encoded master seeds.
Author-email: Ben Westgate <benwestgate@protonmail.com>
Maintainer-email: Ben Westgate <benwestgate@protonmail.com>
License-Expression: MIT
Project-URL: Homepage, https://github.com/benwestgate/python-codex32
Project-URL: Repository, https://github.com/benwestgate/python-codex32
Project-URL: Issues, https://github.com/benwestgate/python-codex32/issues
Project-URL: Changelog, https://github.com/benwestgate/python-codex32/tree/master/CHANGELOG.md
Keywords: bitcoin,HD wallet,BIP32,BIP93,BIP173,BIP350,codex32,cryptography,secret sharing,secrets,entropy,bech32
Classifier: Development Status :: 4 - Beta
Classifier: Intended Audience :: Developers
Classifier: Programming Language :: Python :: 3
Classifier: Programming Language :: Python :: 3 :: Only
Classifier: Programming Language :: Python :: 3.10
Classifier: Programming Language :: Python :: 3.11
Classifier: Programming Language :: Python :: 3.12
Classifier: Programming Language :: Python :: 3.13
Classifier: Programming Language :: Python :: 3.14
Classifier: Operating System :: OS Independent
Classifier: Topic :: Security :: Cryptography
Classifier: Topic :: Software Development :: Libraries
Requires-Python: >=3.10
License-File: LICENSE
Requires-Dist: bip32>=5.0.0
Provides-Extra: dev
Requires-Dist: pytest; extra == "dev"
Requires-Dist: flake8; extra == "dev"
Requires-Dist: mypy; extra == "dev"
Requires-Dist: black; extra == "dev"
Requires-Dist: isort; extra == "dev"
Requires-Dist: ruff; extra == "dev"
Dynamic: license-file
